MANIFEST.in
README.md
bpp.pyx
bpp_h.pxd
setup.py
bin/pairdist
bin/simulate
bpp.egg-info/PKG-INFO
bpp.egg-info/SOURCES.txt
bpp.egg-info/dependency_links.txt
bpp.egg-info/requires.txt
bpp.egg-info/top_level.txt
src/Alignment.cpp
src/Alignment.h
src/AlignmentList.h
src/ModelFactory.cpp
src/ModelFactory.h
src/SiteContainerBuilder.cpp
src/SiteContainerBuilder.h
src/test.h