Metadata-Version: 1.0
Name: bpp
Version: 0.0.12
Summary: Pairwise distances by maximum likelihood
Home-page: https://github.com/kgori/bpp.git
Author: Kevin Gori
Author-email: kgori@ebi.ac.uk
License: UNKNOWN
Platform: UNKNOWN
